dut/alu.sv
`timescale 1ns / 1ps

module alu(clk, en_alu, RD, RA, aluop, out, cy, zy, reset);

	input clk, en_alu, reset;
	input [7:0] RD;		   // RD 8 bit input 
	input [7:0] RA;  	   // RA 8 bit input
	input [4:0] aluop;         //alu operation 
	output [7:0] out;          //alu operation output
	output cy, zy;             //carry and zero flag
	
        reg [8:0]result;           // all operation will take place at this reg

        assign cy=result[8];                // assigning carry to the last bit of result
        assign out=result[7:0];	            //assigning result to ouput of 8 bits data
        assign zy=(result==9'd0)?1'b1:1'b0; // zero flag



        always @(posedge clk) begin
         if(reset) begin
            result <= 0;
         end

         else if(en_alu==1) begin
          case(aluop)
            5'b00000: result <= RD;                         // NOP,STS,LD
            5'b00001: result <= RD + RA;                    // Addition ADD       
            5'b00010: result <= RD + RA + result[8];        // ADC , ROL      
            5'b00011: result <= RD - RA;                    // Subtraction SUB       
            5'b00100: result <= RD & RA;                    // AND_operation       
            5'b00101: result <= RD | RA;                    // OR_operation       
            5'b00110: result <= RD ^ RA;                    // XOR       
            5'b00111: result <= RD + 1'b1;                  // Increment INC       
            5'b01000: result <= RD - 1'b1;                  // Decrement DEC            
            5'b01001: result <= ~ RD;	                    // Complement COM            
            5'b01010: result[7:0] <= RD >> 1;               // Right_shift LSR           
            5'b01011: begin                                 //CP & CPI
                        if(RD < RA) result[8] <= 1;
                        else result[8] <= 0;
                        result[7:0] <= RD;
                      end                     
            5'b01100: result <= {RD[0],result[8],RD[7:1]};   //Right shift through carry ROR            
            5'b01101: result <= ~ RD + 1;                    // 2's Complement NEG            
            5'b01110: result <= {result[8],RD[7],RD[7:1]};   // ASR            
            5'b01111: result <= {RD[3:0],RD[7:4]};           // SWAP            
            5'b11110: result <= RA;                          //buffer for MOV            
            default : result <= 0;       
         endcase
       end

       else begin
          result <= 0;
       end        
      end

endmodule

dut/alu_top.sv
module alu_top(i_clk, i_en_alu, i_RD, i_RA, i_aluop, o_out, o_cy, o_zy);

	input i_clk, i_en_alu;
	input [7:0] i_RD;		   // RD 8 bit input 
	input [7:0] i_RA;  	   // RA 8 bit input
	input [4:0] i_aluop;         //alu operation 
	output [7:0] o_out;          //alu operation output
	output o_cy, o_zy;             //carry and zero flag

        reg i_reset;

        alu alu_dut(i_clk, i_en_alu, i_RD, i_RA, i_aluop, o_out, o_cy, o_zy, i_reset);

        initial begin
           $dumpfile("alu_wave.vcd");
           $dumpvars(0, alu_top);
        end

        initial begin
              i_reset = 0;
          #20 i_reset = 1;
          #30 i_reset = 0;
        end

endmodule

run/alu_wave.vcd
$date
	Sun Sep 18 18:49:31 2022
$end
$version
	Icarus Verilog
$end
$timescale
	1ps
$end
$scope module alu_top $end
$var wire 8 ! i_RA [7:0] $end
$var wire 8 " i_RD [7:0] $end
$var wire 5 # i_aluop [4:0] $end
$var wire 1 $ i_clk $end
$var wire 1 % i_en_alu $end
$var wire 1 & o_zy $end
$var wire 8 ' o_out [7:0] $end
$var wire 1 ( o_cy $end
$var reg 1 ) i_reset $end
$scope module alu_dut $end
$var wire 8 * RA [7:0] $end
$var wire 8 + RD [7:0] $end
$var wire 5 , aluop [4:0] $end
$var wire 1 $ clk $end
$var wire 1 % en_alu $end
$var wire 1 ) reset $end
$var wire 1 & zy $end
$var wire 8 - out [7:0] $end
$var wire 1 ( cy $end
$var reg 9 . result [8:0] $end
$upscope $end
$upscope $end
$enddefinitions $end
#0
$dumpvars
bx .
bx -
b0 ,
b1111 +
b1010 *
0)
x(
bx '
x&
z%
0$
b0 #
b1111 "
b1010 !
$end
#20000
0(
b0 '
b0 -
1&
b0 .
1$
1)
#40000
0$
#50000
0)
#60000
1%
1$
#80000
0$
#100000
b1111 '
b1111 -
0&
b1111 .
1$
#120000
0$
#140000
1$
#160000
0$
#180000
1$
#200000
0$
#220000
1$
#240000
0$
#260000
1$
#280000
0$
#300000
1$
#320000
0$
#340000
1$
#360000
0$
#380000
1$
#390001
0$
b1 #
b1 ,
#410001
b11001 '
b11001 -
b11001 .
1$
#430001
0$
#450001
1$
#470001
0$
#490001
1$
#510001
0$
#530001
1$
#550001
0$
#570001
1$
#590001
0$
#610001
1$
#630001
0$
#650001
1$
#670001
0$
#690001
1$
#710001
0$
#730001
1$
#750001
0$
#770001
1$
#780002
0$
b10 #
b10 ,
#800002
1$
#820002
0$
#840002
1$
#860002
0$
#880002
1$
#900002
0$
#920002
1$
#940002
0$
#960002
1$
#980002
0$
#1000002
1$
#1020002
0$
#1040002
1$
#1060002
0$
#1080002
1$
#1100002
0$
#1120002
1$
#1140002
0$
#1160002
1$
#1170003
0$
b11 #
b11 ,
#1190003
b101 '
b101 -
b101 .
1$
#1210003
0$
#1230003
1$
#1250003
0$
#1270003
1$
#1290003
0$
#1310003
1$
#1330003
0$
#1350003
1$
#1370003
0$
#1390003
1$
#1410003
0$
#1430003
1$
#1450003
0$
#1470003
1$
#1490003
0$
#1510003
1$
#1530003
0$
#1550003
1$
#1560004
0$
b100 #
b100 ,
#1580004
b1010 '
b1010 -
b1010 .
1$
#1600004
0$
#1620004
1$
#1640004
0$
#1660004
1$
#1680004
0$
#1700004
1$
#1720004
0$
#1740004
1$
#1760004
0$
#1780004
1$
#1800004
0$
#1820004
1$
#1840004
0$
#1860004
1$
#1880004
0$
#1900004
1$
#1920004
0$
#1940004
1$
#1950005
0$
b101 #
b101 ,
#1970005
b1111 '
b1111 -
b1111 .
1$
#1990005
0$
#2010005
1$
#2030005
0$
#2050005
1$
#2070005
0$
#2090005
1$
#2110005
0$
#2130005
1$
#2150005
0$
#2170005
1$
#2190005
0$
#2210005
1$
#2230005
0$
#2250005
1$
#2270005
0$
#2290005
1$
#2310005
0$
#2330005
1$
#2340006
0$
b110 #
b110 ,
#2360006
b101 '
b101 -
b101 .
1$
